mv_regex/__init__.py
mv_regex/_version.py
mv_regex/cli/__init__.py
mv_regex/cli/mv.py
mv_regex-0.3.0.dist-info/LICENSE
mv_regex-0.3.0.dist-info/METADATA
mv_regex-0.3.0.dist-info/WHEEL
mv_regex-0.3.0.dist-info/entry_points.txt
mv_regex-0.3.0.dist-info/top_level.txt
mv_regex-0.3.0.dist-info/RECORD
